colorprint/__init__.py
colorprint/core.py
colorprint/test.py
py_colorprinting-0.1.5.dist-info/METADATA
py_colorprinting-0.1.5.dist-info/WHEEL
py_colorprinting-0.1.5.dist-info/top_level.txt
py_colorprinting-0.1.5.dist-info/RECORD
