Metadata-Version: 2.1
Name: py-colorprinting
Version: 0.1.5
Summary: Print colored text in python!
Home-page: 
Author: Arpaia
Author-email: raf@arpaiacorp.com
License: MIT
Requires-Dist: requests <3.0.0,>=2.25.0
